cdktf_cdktf_provider_azurestack/__init__.py
cdktf_cdktf_provider_azurestack/py.typed
cdktf_cdktf_provider_azurestack/_jsii/__init__.py
cdktf_cdktf_provider_azurestack/_jsii/provider-azurestack@9.0.0.jsii.tgz
cdktf_cdktf_provider_azurestack/availability_set/__init__.py
cdktf_cdktf_provider_azurestack/data_azurestack_availability_set/__init__.py
cdktf_cdktf_provider_azurestack/data_azurestack_client_config/__init__.py
cdktf_cdktf_provider_azurestack/data_azurestack_dns_zone/__init__.py
cdktf_cdktf_provider_azurestack/data_azurestack_image/__init__.py
cdktf_cdktf_provider_azurestack/data_azurestack_key_vault/__init__.py
cdktf_cdktf_provider_azurestack/data_azurestack_key_vault_access_policy/__init__.py
cdktf_cdktf_provider_azurestack/data_azurestack_key_vault_key/__init__.py
cdktf_cdktf_provider_azurestack/data_azurestack_key_vault_secret/__init__.py
cdktf_cdktf_provider_azurestack/data_azurestack_lb/__init__.py
cdktf_cdktf_provider_azurestack/data_azurestack_lb_backend_address_pool/__init__.py
cdktf_cdktf_provider_azurestack/data_azurestack_lb_rule/__init__.py
cdktf_cdktf_provider_azurestack/data_azurestack_local_network_gateway/__init__.py
cdktf_cdktf_provider_azurestack/data_azurestack_managed_disk/__init__.py
cdktf_cdktf_provider_azurestack/data_azurestack_network_interface/__init__.py
cdktf_cdktf_provider_azurestack/data_azurestack_network_security_group/__init__.py
cdktf_cdktf_provider_azurestack/data_azurestack_platform_image/__init__.py
cdktf_cdktf_provider_azurestack/data_azurestack_public_ip/__init__.py
cdktf_cdktf_provider_azurestack/data_azurestack_public_ips/__init__.py
cdktf_cdktf_provider_azurestack/data_azurestack_resource_group/__init__.py
cdktf_cdktf_provider_azurestack/data_azurestack_resources/__init__.py
cdktf_cdktf_provider_azurestack/data_azurestack_route_table/__init__.py
cdktf_cdktf_provider_azurestack/data_azurestack_storage_account/__init__.py
cdktf_cdktf_provider_azurestack/data_azurestack_storage_container/__init__.py
cdktf_cdktf_provider_azurestack-9.0.0.dist-info/LICENSE
cdktf_cdktf_provider_azurestack-9.0.0.dist-info/METADATA
cdktf_cdktf_provider_azurestack-9.0.0.dist-info/WHEEL
cdktf_cdktf_provider_azurestack-9.0.0.dist-info/top_level.txt
cdktf_cdktf_provider_azurestack-9.0.0.dist-info/RECORD
